odoo10_addon_stock_lot_sale_tracking-10.0.1.0.1-py3.8-nspkg.pth
odoo/addons/stock_lot_sale_tracking/README.rst
odoo/addons/stock_lot_sale_tracking/__init__.py
odoo/addons/stock_lot_sale_tracking/__manifest__.py
odoo/addons/stock_lot_sale_tracking/i18n/stock_lot_sale_tracking.pot
odoo/addons/stock_lot_sale_tracking/models/__init__.py
odoo/addons/stock_lot_sale_tracking/models/stock_production_lot.py
odoo/addons/stock_lot_sale_tracking/report/__init__.py
odoo/addons/stock_lot_sale_tracking/report/stock_lot_sale_report.py
odoo/addons/stock_lot_sale_tracking/report/stock_lot_sale_report.xml
odoo/addons/stock_lot_sale_tracking/security/security.xml
odoo/addons/stock_lot_sale_tracking/static/description/icon.png
odoo10_addon_stock_lot_sale_tracking-10.0.1.0.1.dist-info/METADATA
odoo10_addon_stock_lot_sale_tracking-10.0.1.0.1.dist-info/WHEEL
odoo10_addon_stock_lot_sale_tracking-10.0.1.0.1.dist-info/namespace_packages.txt
odoo10_addon_stock_lot_sale_tracking-10.0.1.0.1.dist-info/top_level.txt
odoo10_addon_stock_lot_sale_tracking-10.0.1.0.1.dist-info/RECORD
