Metadata-Version: 2.1
Name: odoo10-addon-stock-lot-sale-tracking
Version: 10.0.1.0.1
Summary: This addon allows to retrieve all customer deliveries impacted by a lot
Home-page: https://github.com/OCA/stock-logistics-warehouse/stock_lot_sale_tracking
Author: ACSONE SA/NV,Odoo Community Association (OCA)
Author-email: support@odoo-community.org
License: AGPL-3
Platform: UNKNOWN
Classifier: Programming Language :: Python
Classifier: Framework :: Odoo
Classifier: Framework :: Odoo :: 10.0
Classifier: License :: OSI Approved :: GNU Affero General Public License v3
Requires-Python: ~=2.7
Requires-Dist: odoo (<10.1dev,>=10.0)
